chunkup
