Metadata-Version: 1.0
Name: chunkup
Version: 0.2.1
Summary: chunks up audio
Home-page: https://github.com/JoFrhwld/chunkup
Author: Josef Fruehwald
Author-email: jofrhwld@gmail.com
License: MIT
Platform: UNKNOWN
